captif_db/__init__.py
captif_db/db/__init__.py
captif_db/db/constants.py
captif_db/db/dbsession.py
captif_db/db/docs.py
captif_db/db/models/__init__.py
captif_db/db/models/base.py
captif_db/db/models/continuous/moisture.py
captif_db/db/models/continuous/pore_pressure.py
captif_db/db/models/continuous/strain.py
captif_db/db/models/continuous/suction.py
captif_db/db/models/continuous/temperature.py
captif_db/db/models/interval/deflection.py
captif_db/db/models/interval/strain.py
captif_db/db/models/interval/surface_profile.py
captif_db/db/models/interval/texture.py
captif_db/db/models/project.py
captif_db/db/models/reference.py
captif_db/db/models/track.py
captif_db/helpers/file_operations.py
captif_db/helpers/models.py
captif_db/helpers/parse_datetime.py
captif_db/helpers/parse_number.py
captif_db/loaders/__init__.py
captif_db/loaders/continuous_loaders.py
captif_db/loaders/generic_loaders.py
captif_db/loaders/helpers.py
captif_db/loaders/interval_loaders.py
captif_db/loaders/misc_loaders.py
captif_db/loaders/project_loaders.py
captif_db/loaders/schema.py
captif_db/logging.py
captif_db-0.13.dist-info/LICENSE
captif_db-0.13.dist-info/WHEEL
captif_db-0.13.dist-info/METADATA
captif_db-0.13.dist-info/RECORD
