Metadata-Version: 2.1
Name: captif-db
Version: 0.13
Summary: 
License: MIT
Keywords: CAPTIF
Author: John Bull
Author-email: john.bull@nzta.govt.nz
Requires-Python: >=3.8,<3.10
Classifier: License :: OSI Approved :: MIT License
Classifier: Programming Language :: Python :: 3
Classifier: Programming Language :: Python :: 3.8
Classifier: Programming Language :: Python :: 3.9
Requires-Dist: captif-data-structures (>=0.12)
Requires-Dist: captif-db-config (>=0.10)
Requires-Dist: captif-slp (>=0.10)
Requires-Dist: mysqlclient (>=2.0.3,<3.0.0)
Requires-Dist: numpy (>=1.19.1,<2.0.0)
Requires-Dist: pandas (>=1.1.0,<2.0.0)
Requires-Dist: schema (>=0.7.2,<0.8.0)
Requires-Dist: toml (>=0.10.1,<0.11.0)
